darren.py
darren_utils/FileUtils.py
darren_utils/MeUtils.py
darren_utils/Proxy_tools.py
darren_utils/StringUtils.py
darren_utils/SystemUtils.py
darren_utils/ThreadPool.py
darren_utils/TimeUtils.py
darren_utils/__init__.py
darren_utils/config_utils.py
darren_utils/darren.py
darren_utils/darren_clipboard.py
darren_utils/darren_http_class.py
darren_utils/darren_module.py
darren_utils/darren_ret.py
darren_utils/devices_utils.py
darren_utils/fn_net_work.py
darren_utils/main.py
darren_utils/setup.py
darren_utils/test.py
darren_utils/encry/HashUtils.py
darren_utils/encry/HmacUtils.py
darren_utils/encry/__init__.py
darren_utils/encry/darren_3des.py
darren_utils/encry/darren_3des_js.py
darren_utils/encry/darren_aes.py
darren_utils/encry/darren_des.py
darren_utils/encry/darren_rc4.py
darren_utils/encry/darren_rsa.py
darren_utils/encry/darren_sm2.py
darren_utils/encry/darren_sm3.py
darren_utils/encry/darren_sm4.py
darren_utils/encry/js_rsa.py
darren_utils/proxy/Proxy_tools.py
darren_utils/proxy/__init__.py
darren_utils/proxy/common_proxy.py
darren_utils/proxy/proxy_class.py
darren_utils/proxy/proxy_config.py
darren_utils-0.2.1.302.dist-info/METADATA
darren_utils-0.2.1.302.dist-info/WHEEL
darren_utils-0.2.1.302.dist-info/top_level.txt
darren_utils-0.2.1.302.dist-info/RECORD
