Metadata-Version: 2.4
Name: darren_utils
Version: 0.2.1.302
Summary: 一个功能丰富的工具包
Home-page: https://github.com/Darren5211314
Author: Darren
Author-email: Darren <2775856@qq.com>
License: MIT
Project-URL: Homepage, https://github.com/Darren5211314
Project-URL: Repository, https://github.com/Darren5211314
Classifier: Development Status :: 3 - Alpha
Classifier: Intended Audience :: Developers
Classifier: License :: OSI Approved :: MIT License
Classifier: Programming Language :: Python :: 3
Classifier: Programming Language :: Python :: 3.7
Classifier: Programming Language :: Python :: 3.8
Classifier: Programming Language :: Python :: 3.9
Classifier: Programming Language :: Python :: 3.10
Requires-Python: >=3.7
Requires-Dist: setuptools
Requires-Dist: requests
Requires-Dist: pyarmor>=9.0
Requires-Dist: cryptography
Requires-Dist: gmssl
Requires-Dist: send2trash
Requires-Dist: pyperclip
Requires-Dist: psutil
Requires-Dist: pillow
Requires-Dist: redis
Requires-Dist: httpx[http2]
Dynamic: author
Dynamic: home-page
Dynamic: requires-python
